fastmock/__init__.py
fastmock/decorator.py
fastmock/middleware.py
fastmock/model.py
fastmock/request_response.py
fastmock/tools.py
tests/__init__.py
tests/device.py
tests/test_fastmock_data_retrieve_order.py
tests/test_fastmock_decorator.py
tests/test_fastmock_middleware_openapi.py
tests/test_fastmock_parameter_activate.py
tests/test_fastmock_parameter_element_size.py
tests/test_fastmock_parameter_response_status.py
tests/test_fastmock_parameter_type.py
tests/test_fastmock_response_type.py
tests/clients/__init__.py
tests/clients/decorator_client.py
tests/clients/decorator_initialization_client.py
tests/clients/header_client.py
tests/clients/middleware_client.py
fastmock-0.1.1.dist-info/LICENSE
fastmock-0.1.1.dist-info/METADATA
fastmock-0.1.1.dist-info/WHEEL
fastmock-0.1.1.dist-info/top_level.txt
fastmock-0.1.1.dist-info/RECORD
