Metadata-Version: 2.1
Name: fastmock
Version: 0.1.1
Summary: FastAPI middleware for mocking responses based on Pydantic models response
Home-page: https://github.com/tpemeja/fastmock
Author: Tanguy PEMEJA
Author-email: tanguy.pemeja@gmail.com
Classifier: Programming Language :: Python :: 3
Classifier: License :: OSI Approved :: MIT License
Classifier: Operating System :: OS Independent
Requires-Python: >=3.10
License-File: LICENSE
